{
  "products": [
    {
      "id": 1,
      "name": "Computer",
      "price": 5000,
      "quantity": 100,
      "selected": false,
      "available": true
    },
    {
      "id": 2,
      "name": "Printer",
      "price": 4300,
      "quantity": 600,
      "selected": true,
      "available": true
    },
    {
      "name": "laravel",
      "price": 4000,
      "quantity": 450,
      "selected": false,
      "available": true,
      "id": 4
    },
    {
      "id": 5,
      "name": "joel",
      "price": "4011",
      "quantity": "111111",
      "selected": true,
      "available": true
    },
    {
      "name": "joel tchoufa",
      "price": 0,
      "quantity": 0,
      "selected": false,
      "available": true,
      "id": 6
    }
  ]
}